astral/__init__.py
astral/__main__.py
astral/geocoder.py
astral/julian.py
astral/location.py
astral/moon.py
astral/py.typed
astral/sidereal.py
astral/sun.py
astral/table4.py
astral-3.1.dist-info/LICENSE
astral-3.1.dist-info/WHEEL
astral-3.1.dist-info/METADATA
astral-3.1.dist-info/RECORD
